Metadata-Version: 2.1
Name: downgram
Version: 0.2.1
Summary: DownGram can download media from Telegram, using Telethon.
Home-page: https://github.com/josopu/DownGram
Author: josopu
Author-email: piperinoxi@gmail.com
License: UNKNOWN
Platform: UNKNOWN
Classifier: Programming Language :: Python :: 3
